MANIFEST.in
readme.md
setup.py
mqreceive/__init__.py
mqreceive/broker.py
mqreceive/collecting.py
mqreceive/data.py
mqreceive/receiving.py
mqreceive.egg-info/PKG-INFO
mqreceive.egg-info/SOURCES.txt
mqreceive.egg-info/dependency_links.txt
mqreceive.egg-info/requires.txt
mqreceive.egg-info/top_level.txt
mqreceive/test/__init__.py
mqreceive/test/test_broker.py
mqreceive/test/test_data_identifier.py